Git/__init__.py
Git/__main__.py
Git/application.py
Git/cache.py
Git/git.py
Git/print.py
Git/repository.py
git_unite-1.0.1.dist-info/METADATA
git_unite-1.0.1.dist-info/WHEEL
git_unite-1.0.1.dist-info/entry_points.txt
git_unite-1.0.1.dist-info/licenses/LICENSE
git_unite-1.0.1.dist-info/RECORD
