Metadata-Version: 2.4
Name: git-unite
Version: 1.0.1
Summary: Manage multiple git repositories in one place.
Project-URL: Homepage, https://gitlab.com/0tanay/git
Project-URL: Repository, https://gitlab.com/0tanay/git.git
Project-URL: Issues, https://gitlab.com/0tanay/git/-/issues
License-File: LICENSE
Requires-Dist: click
Requires-Dist: gitpython
Requires-Dist: pyyaml
